partitionsets/__init__.py
partitionsets/__main__.py
partitionsets/cli.py
partitionsets/ordered_set.py
partitionsets/partition.py
test/__init__.py
test/test_ordered_set.py
test/test_partition.py
test/test_partitionsets.py
partitionsets-2022.7.23.dist-info/LICENSE
partitionsets-2022.7.23.dist-info/METADATA
partitionsets-2022.7.23.dist-info/WHEEL
partitionsets-2022.7.23.dist-info/entry_points.txt
partitionsets-2022.7.23.dist-info/top_level.txt
partitionsets-2022.7.23.dist-info/RECORD
