Metadata-Version: 2.1
Name: partitionsets
Version: 2022.7.23
Summary: Implementation of dict supporting context managed thread safe and mutable iterations through a lock.
Home-page: https://git.sr.ht/~sthagen/partitionsets
Author: Stefan Hagen
Author-email: stefan@hagen.link
Maintainer: Stefan Hagen
Maintainer-email: stefan@hagen.link
Project-URL: Bug Tracker, https://github.com/sthagen/partitionsets/issues
Project-URL: Documentation, https://codes.dilettant.life/docs/partitionsets
Project-URL: Source Code, https://git.sr.ht/~sthagen/partitionsets
Keywords: developer-tools,partitions,sets
Classifier: Development Status :: 5 - Production/Stable
Classifier: Intended Audience :: Developers
Classifier: License :: OSI Approved :: MIT License
Classifier: Programming Language :: Python :: 3.10
Classifier: Programming Language :: Python :: 3.8
Classifier: Programming Language :: Python :: 3.9
Classifier: Topic :: Utilities
Requires-Python: >=3.8
License-File: LICENSE
